ccspectools.py
ccspectools-2.0.0.dist-info/COPYING
ccspectools-2.0.0.dist-info/METADATA
ccspectools-2.0.0.dist-info/WHEEL
ccspectools-2.0.0.dist-info/top_level.txt
ccspectools-2.0.0.dist-info/RECORD
